naply/__init__.py
naply/attention.py
naply/base_model_loader.py
naply/cli.py
naply/config.py
naply/cpu_optimize.py
naply/data.py
naply/easy.py
naply/easy_finetune.py
naply/finetune.py
naply/finetune_trainer.py
naply/functional.py
naply/large_dataset.py
naply/layers.py
naply/methods.py
naply/model.py
naply/nn.py
naply/optim.py
naply/powerful_text_model.py
naply/specialists.py
naply/tensor.py
naply/test_finetune_verification.py
naply/text_enhanced.py
naply/tokenizer.py
naply/trainer.py
naply/training_control.py
naply/transformer.py
naply/utils.py
naply/image/__init__.py
naply/image/dataset.py
naply/image/diffusion.py
naply/image/inference.py
naply/image/trainer.py
naply/image/unet.py
naply/image/vae.py
naply/tests/test_naply.py
naply/trainer/__init__.py
naply/trainer/base_trainer.py
naply/trainer/checkpoint.py
naply/trainer/gpu_manager.py
naply/trainer/logger.py
naply/voice/__init__.py
naply/voice/dataset.py
naply/voice/decoder.py
naply/voice/encoder.py
naply/voice/inference.py
naply/voice/spectrogram.py
naply/voice/trainer.py
naply/voice/vocoder.py
naply-4.3.2.dist-info/licenses/LICENSE
naply-4.3.2.dist-info/METADATA
naply-4.3.2.dist-info/WHEEL
naply-4.3.2.dist-info/entry_points.txt
naply-4.3.2.dist-info/top_level.txt
naply-4.3.2.dist-info/RECORD
