Metadata-Version: 2.4
Name: naply
Version: 4.3.2
Summary: 🚀 The Most Powerful AI Framework: Build & Fine-Tune ChatGPT-Level Models - CPU-Optimized, LoRA/QLoRA, Production-Ready
Author: NAPLY Team
Author-email: NAPLY Team <naply511@gmail.com>
Maintainer-email: NAPLY Team <naply511@gmail.com>
License-Expression: MIT
Project-URL: Homepage, https://github.com/naply-ai/naply
Project-URL: Documentation, https://github.com/naply-ai/naply#readme
Project-URL: Repository, https://github.com/naply-ai/naply
Project-URL: Issues, https://github.com/naply-ai/naply/issues
Project-URL: Changelog, https://github.com/naply-ai/naply/releases
Keywords: ai,machine-learning,deep-learning,neural-network,transformer,gpt,language-model,llm,nlp,training,from-scratch,cpu,no-gpu,tokenizer,bpe,chatgpt,pytorch-alternative,tensorflow-alternative,lightweight,production-ready,autograd,automatic-differentiation,fine-tuning,lora,qlora,peft,adapters,transfer-learning
Classifier: Development Status :: 4 - Beta
Classifier: Intended Audience :: Developers
Classifier: Intended Audience :: Science/Research
Classifier: Intended Audience :: Education
Classifier: Operating System :: OS Independent
Classifier: Operating System :: Microsoft :: Windows
Classifier: Operating System :: POSIX :: Linux
Classifier: Operating System :: MacOS
Classifier: Programming Language :: Python :: 3
Classifier: Programming Language :: Python :: 3.8
Classifier: Programming Language :: Python :: 3.9
Classifier: Programming Language :: Python :: 3.10
Classifier: Programming Language :: Python :: 3.11
Classifier: Programming Language :: Python :: 3.12
Classifier: Topic :: Scientific/Engineering :: Artificial Intelligence
Classifier: Topic :: Software Development :: Libraries :: Python Modules
Classifier: Topic :: Software Development :: Libraries :: Application Frameworks
Classifier: Topic :: Text Processing :: Linguistic
Requires-Python: >=3.8
License-File: LICENSE
Requires-Dist: numpy>=1.21.0
Requires-Dist: tqdm>=4.65.0
Provides-Extra: dev
Requires-Dist: pytest>=7.0.0; extra == "dev"
Requires-Dist: pytest-cov>=4.0.0; extra == "dev"
Requires-Dist: black>=23.0.0; extra == "dev"
Requires-Dist: mypy>=1.0.0; extra == "dev"
Requires-Dist: flake8>=6.0.0; extra == "dev"
Provides-Extra: finetune
Requires-Dist: safetensors>=0.4.0; extra == "finetune"
Requires-Dist: pandas>=2.0.0; extra == "finetune"
Provides-Extra: all
Requires-Dist: numpy>=1.21.0; extra == "all"
Requires-Dist: tqdm>=4.65.0; extra == "all"
Requires-Dist: colorama>=0.4.6; extra == "all"
Requires-Dist: safetensors>=0.4.0; extra == "all"
Requires-Dist: pandas>=2.0.0; extra == "all"
Provides-Extra: gpu
Requires-Dist: numpy>=1.21.0; extra == "gpu"
Requires-Dist: tqdm>=4.65.0; extra == "gpu"
Dynamic: author
Dynamic: license-file
Dynamic: requires-python
